{
  "exclusion_criteria": [],
  "inclusion_criteria": {
    "required": [
      {
        "criterion": "Describes end-to-end code-switching systems.",
        "source": "criteria_mds/2507.07741.md",
        "topic_ids": [
          "S1"
        ]
      }
    ]
  },
  "sources": [
    "criteria_mds/2507.07741.md"
  ],
  "summary": "Parsed screening criteria from criteria_mds/2507.07741.md",
  "summary_topics": [
    {
      "description": "Code-Switching in End-to-End Automatic Speech Recognition:",
      "id": "S1"
    }
  ],
  "topic": "Code-Switching in End-to-End Automatic Speech Recognition:",
  "topic_definition": "Code-switching in end-to-end automatic speech recognition is the recognition of multilingual speech that alternates between languages within an utterance using a single model that maps audio directly to transcriptions."
}
